{
  "求和器": {
    "component_box": [
      135.0,
      175.0,
      192.0,
      232.0
    ],
    "connections": {
      "input": [
        {
          "name": "vo_ref",
          "count": 1
        },
        {
          "name": "vo",
          "count": 1
        }
      ],
      "output": [
        {
          "name": "PI controller",
          "count": 1
        }
      ],
      "inout": []
    }
  },
  "Polarity Detection": {
    "component_box": [
      390.0,
      17.0,
      567.0,
      115.0
    ],
    "connections": {
      "input": [
        {
          "name": "PLL",
          "count": 1
        }
      ],
      "output": [
        {
          "name": "DMS Modulator",
          "count": 1
        }
      ],
      "inout": []
    }
  },
  "PLL": {
    "component_box": [
      215.0,
      26.0,
      329.0,
      107.0
    ],
    "connections": {
      "input": [
        {
          "name": "vin",
          "count": 1
        }
      ],
      "output": [
        {
          "name": "Polarity Detection",
          "count": 1
        }
      ],
      "inout": []
    }
  },
  "PI controller": {
    "component_box": [
      259.0,
      151.0,
      412.0,
      257.0
    ],
    "connections": {
      "input": [
        {
          "name": "求和器",
          "count": 1
        }
      ],
      "output": [
        {
          "name": "DMS Modulator",
          "count": 1
        }
      ],
      "inout": []
    }
  },
  "DMS Modulator": {
    "component_box": [
      474.0,
      162.0,
      727.0,
      246.0
    ],
    "connections": {
      "input": [
        {
          "name": "Polarity Detection",
          "count": 1
        },
        {
          "name": "PI controller",
          "count": 1
        }
      ],
      "output": [
        {
          "name": "S1–S8",
          "count": 1
        }
      ],
      "inout": []
    }
  }
}