{
  "Comparator": {
    "component_box": [
      102.0,
      104.0,
      177.0,
      193.0
    ],
    "connections": {
      "input": [
        {
          "name": "V_REF",
          "count": 1
        },
        {
          "name": "V_OUT",
          "count": 1
        }
      ],
      "output": [
        {
          "name": "Controller",
          "count": 1
        }
      ],
      "inout": []
    }
  },
  "Load": {
    "component_box": [
      479.0,
      290.0,
      514.0,
      326.0
    ],
    "connections": {
      "input": [],
      "output": [],
      "inout": [
        {
          "name": "VOUT",
          "count": 1
        },
        {
          "name": "Ground",
          "count": 1
        }
      ]
    }
  },
  "Controller": {
    "component_box": [
      211.0,
      45.0,
      292.0,
      253.0
    ],
    "connections": {
      "input": [
        {
          "name": "Comparator",
          "count": 1
        }
      ],
      "output": [
        {
          "name": "Power MOSFETs",
          "count": 1
        }
      ],
      "inout": []
    }
  },
  "Power MOSFETs": {
    "component_box": [
      362.0,
      69.0,
      487.0,
      202.0
    ],
    "connections": {
      "input": [
        {
          "name": "Controller",
          "count": 1
        }
      ],
      "output": [],
      "inout": [
        {
          "name": "VIN",
          "count": 1
        },
        {
          "name": "Load",
          "count": 1
        },
        {
          "name": "Comparator",
          "count": 1
        }
      ]
    }
  }
}