{
  "Common Mode": {
    "component_box": [
      449.0,
      168.0,
      564.0,
      248.0
    ],
    "connections": {
      "input": [
        {
          "name": "Σ (Summing Junction)",
          "count": 1
        }
      ],
      "output": [],
      "inout": [
        {
          "name": "Switched-capacitor",
          "count": 1
        }
      ]
    }
  },
  "SR latch": {
    "component_box": [
      51.0,
      105.0,
      144.0,
      304.0
    ],
    "connections": {
      "input": [
        {
          "name": "Comparator",
          "count": 1
        },
        {
          "name": "op amp",
          "count": 1
        }
      ],
      "output": [],
      "inout": [
        {
          "name": "SW",
          "count": 1
        }
      ]
    }
  },
  "op amp": {
    "component_box": [
      160.0,
      218.0,
      239.0,
      315.0
    ],
    "connections": {
      "input": [
        {
          "name": "Σ (Summing Junction)",
          "count": 1
        },
        {
          "name": "Σ (Summing Junction)",
          "count": 1
        }
      ],
      "output": [
        {
          "name": "SR latch",
          "count": 1
        }
      ],
      "inout": []
    }
  },
  "Comparator": {
    "component_box": [
      160.0,
      101.0,
      238.0,
      196.0
    ],
    "connections": {
      "input": [],
      "output": [
        {
          "name": "SR latch",
          "count": 1
        }
      ],
      "inout": [
        {
          "name": "Σ (Summing Junction)",
          "count": 1
        }
      ]
    }
  },
  "2I": {
    "component_box": [
      698.0,
      430.0,
      735.0,
      470.0
    ],
    "connections": {
      "input": [],
      "output": [],
      "inout": [
        {
          "name": "SW",
          "count": 1
        },
        {
          "name": "ground",
          "count": 1
        }
      ]
    }
  },
  "Σ (Summing Junction)": {
    "component_box": [
      304.0,
      184.0,
      342.0,
      221.0
    ],
    "connections": {
      "input": [
        {
          "name": "Vs",
          "count": 1
        }
      ],
      "output": [],
      "inout": [
        {
          "name": "Comparator",
          "count": 1
        },
        {
          "name": "Common Mode",
          "count": 1
        }
      ]
    }
  },
  "I": {
    "component_box": [
      778.0,
      63.0,
      815.0,
      102.0
    ],
    "connections": {
      "input": [],
      "output": [],
      "inout": [
        {
          "name": "C",
          "count": 1
        },
        {
          "name": "",
          "count": 1
        }
      ]
    }
  },
  "Switched-capacitor": {
    "component_box": [
      640.0,
      127.0,
      803.0,
      375.0
    ],
    "connections": {
      "input": [
        {
          "name": "Current source",
          "count": 1
        },
        {
          "name": "I",
          "count": 1
        },
        {
          "name": "2I",
          "count": 1
        }
      ],
      "output": [],
      "inout": [
        {
          "name": "Common Mode",
          "count": 1
        },
        {
          "name": "SR latch",
          "count": 1
        }
      ]
    }
  },
  "Current source": {
    "component_box": [
      623.0,
      64.0,
      660.0,
      102.0
    ],
    "connections": {
      "input": [],
      "output": [],
      "inout": [
        {
          "name": "Common Mode",
          "count": 1
        },
        {
          "name": "Switched-capacitor",
          "count": 1
        },
        {
          "name": "I",
          "count": 1
        }
      ]
    }
  }
}