{
  "LT3080": {
    "component_box": [
      172.0,
      376.0,
      316.0,
      459.0
    ],
    "connections": {
      "input": [],
      "output": [
        {
          "name": "DUT",
          "count": 1
        },
        {
          "name": "DUT",
          "count": 1
        },
        {
          "name": "Keysight 34465A",
          "count": 1
        }
      ],
      "inout": [
        {
          "name": "Keysight E36312A",
          "count": 1
        }
      ]
    }
  },
  "Yokogawa 701922": {
    "component_box": [
      417.0,
      214.0,
      593.0,
      309.0
    ],
    "connections": {
      "input": [],
      "output": [],
      "inout": [
        {
          "name": "DUT",
          "count": 1
        },
        {
          "name": "Switch",
          "count": 1
        }
      ]
    }
  },
  "Keysight E36312A": {
    "component_box": [
      9.0,
      377.0,
      148.0,
      458.0
    ],
    "connections": {
      "input": [],
      "output": [
        {
          "name": "DUT",
          "count": 1
        }
      ],
      "inout": []
    }
  },
  "Switch": {
    "component_box": [
      415.0,
      334.0,
      434.0,
      372.0
    ],
    "connections": {
      "input": [
        {
          "name": "DUT",
          "count": 1
        }
      ],
      "output": [],
      "inout": [
        {
          "name": "Keysight 34465A",
          "count": 1
        }
      ]
    }
  },
  "Agilent 33250A": {
    "component_box": [
      11.0,
      28.0,
      151.0,
      123.0
    ],
    "connections": {
      "input": [],
      "output": [],
      "inout": [
        {
          "name": "Switch",
          "count": 1
        }
      ]
    }
  },
  "E5061B": {
    "component_box": [
      212.0,
      30.0,
      367.0,
      123.0
    ],
    "connections": {
      "input": [],
      "output": [],
      "inout": [
        {
          "name": "Switch",
          "count": 1
        },
        {
          "name": "Switch",
          "count": 1
        }
      ]
    }
  },
  "Yokogawa DLM2054": {
    "component_box": [
      438.0,
      32.0,
      605.0,
      125.0
    ],
    "connections": {
      "input": [],
      "output": [],
      "inout": [
        {
          "name": "Switch",
          "count": 1
        },
        {
          "name": "Power",
          "count": 1
        }
      ]
    }
  },
  "Keysight 34465A": {
    "component_box": [
      356.0,
      377.0,
      496.0,
      457.0
    ],
    "connections": {
      "input": [
        {
          "name": "DUT",
          "count": 1
        }
      ],
      "output": [],
      "inout": []
    }
  },
  "DUT": {
    "component_box": [
      216.0,
      212.0,
      374.0,
      319.0
    ],
    "connections": {
      "input": [
        {
          "name": "Minicircuits ADT16T",
          "count": 1
        },
        {
          "name": "LT3080",
          "count": 1
        }
      ],
      "output": [
        {
          "name": "Yokogawa 701922",
          "count": 1
        },
        {
          "name": "Keysight 34465A",
          "count": 1
        }
      ],
      "inout": []
    }
  }
}